quma/__init__.py
quma/conn.py
quma/cursor.py
quma/database.py
quma/exc.py
quma/namespace.py
quma/pool.py
quma/query.py
quma/script.py
quma/provider/__init__.py
quma/provider/mysql.py
quma/provider/postgresql.py
quma/provider/sqlite.py
quma/tests/__init__.py
quma/tests/conftest.py
quma/tests/test_conn.py
quma/tests/test_db.py
quma/tests/test_mysql.py
quma/tests/test_postgres.py
quma/tests/util.py
quma/tests/fixtures/__init__.py
quma/tests/fixtures/scripts/pyformat/addresses/all.sql
quma/tests/fixtures/scripts/pyformat/addresses/by_user.sql
quma/tests/fixtures/scripts/pyformat/users/__init__.py
quma/tests/fixtures/scripts/pyformat/users/add.sql
quma/tests/fixtures/scripts/pyformat/users/all.sql
quma/tests/fixtures/scripts/pyformat/users/by_city.sql
quma/tests/fixtures/scripts/pyformat/users/by_email.sql
quma/tests/fixtures/scripts/pyformat/users/by_name.sql
quma/tests/fixtures/scripts/pyformat/users/mysql_prepare.sql
quma/tests/fixtures/scripts/pyformat/users/none.sql
quma/tests/fixtures/scripts/pyformat/users/pgsql_prepare.sql
quma/tests/fixtures/scripts/pyformat/users/remove.sql
quma/tests/fixtures/scripts/pyformat/users/update.sql
quma/tests/fixtures/scripts/qmark/__init__.py
quma/tests/fixtures/scripts/qmark/get_city.sql
quma/tests/fixtures/scripts/qmark/get_users.sql
quma/tests/fixtures/scripts/qmark/addresses/all.sql
quma/tests/fixtures/scripts/qmark/addresses/by_user.sql
quma/tests/fixtures/scripts/qmark/addresses/by_zip.sql
quma/tests/fixtures/scripts/qmark/users/__init__.py
quma/tests/fixtures/scripts/qmark/users/add.sql
quma/tests/fixtures/scripts/qmark/users/all.sql
quma/tests/fixtures/scripts/qmark/users/by_city.sql
quma/tests/fixtures/scripts/qmark/users/by_email.sql
quma/tests/fixtures/scripts/qmark/users/by_name.sql
quma/tests/fixtures/scripts/qmark/users/by_name_tmpl.msql
quma/tests/fixtures/scripts/qmark/users/get_test.sql
quma/tests/fixtures/scripts/qmark/users/none.sql
quma/tests/fixtures/scripts/qmark/users/remove.sql
quma-0.1.1.dist-info/licenses/LICENSE.rst
quma-0.1.1.dist-info/WHEEL
quma-0.1.1.dist-info/METADATA
quma-0.1.1.dist-info/RECORD
