Metadata-Version: 2.4
Name: quma
Version: 0.1.1
Summary: A SQL/database library
Keywords: sql,database
Author-email: ebene fünf GmbH <info@ebenefuenf.de>
Requires-Python: >=3.8
Classifier: Development Status :: 5 - Production/Stable
Classifier: Intended Audience :: Developers
Classifier: License :: OSI Approved :: MIT License
Classifier: Programming Language :: Python
Classifier: Programming Language :: Python :: 3.8
Classifier: Programming Language :: Python :: 3.9
Classifier: Programming Language :: Python :: 3.10
Classifier: Programming Language :: Python :: 3.11
Classifier: Programming Language :: Python :: 3.12
Classifier: Programming Language :: Python :: 3 :: Only
Classifier: Topic :: Database :: Front-Ends
License-File: LICENSE.rst
Requires-Dist: ruff ; extra == "dev"
Requires-Dist: sphinx ; extra == "docs"
Requires-Dist: sphinx-autobuild ; extra == "docs"
Requires-Dist: mysqlclient ; extra == "mysql"
Requires-Dist: psycopg2 ; extra == "postgres" and ( implementation_name=='cpython')
Requires-Dist: psycopg2cffi ; extra == "postgres" and ( implementation_name=='pypy')
Requires-Dist: mako ; extra == "templates"
Requires-Dist: pytest ; extra == "test"
Requires-Dist: pytest-cov ; extra == "test"
Requires-Dist: coverage-conditional-plugin ; extra == "test"
Project-URL: Documentation, https://quma.readthedocs.io
Project-URL: Homepage, https://github.com/ebenefuenf/quma
Project-URL: Issues, https://github.com/ebenefuenf/quma/issues
Provides-Extra: dev
Provides-Extra: docs
Provides-Extra: mysql
Provides-Extra: postgres
Provides-Extra: templates
Provides-Extra: test
